{"nodes": [{"id": "g_ai_tk_ops_assistant_v3_apps_py_runtime_src_repositories_video_deconstruction_repository_py", "label": "video_deconstruction_repository.py", "file_type": "code", "source_file": "G:\\AI\\TK-OPS-ASSISTANT-V3\\apps\\py-runtime\\src\\repositories\\video_deconstruction_repository.py", "source_location": "L1"}, {"id": "video_deconstruction_repository_storedvideostagerun", "label": "StoredVideoStageRun", "file_type": "code", "source_file": "G:\\AI\\TK-OPS-ASSISTANT-V3\\apps\\py-runtime\\src\\repositories\\video_deconstruction_repository.py", "source_location": "L13"}, {"id": "video_deconstruction_repository_videodeconstructionrepository", "label": "VideoDeconstructionRepository", "file_type": "code", "source_file": "G:\\AI\\TK-OPS-ASSISTANT-V3\\apps\\py-runtime\\src\\repositories\\video_deconstruction_repository.py", "source_location": "L24"}, {"id": "video_deconstruction_repository_videodeconstructionrepository_init", "label": ".__init__()", "file_type": "code", "source_file": "G:\\AI\\TK-OPS-ASSISTANT-V3\\apps\\py-runtime\\src\\repositories\\video_deconstruction_repository.py", "source_location": "L25"}, {"id": "video_deconstruction_repository_videodeconstructionrepository_list_stage_runs", "label": ".list_stage_runs()", "file_type": "code", "source_file": "G:\\AI\\TK-OPS-ASSISTANT-V3\\apps\\py-runtime\\src\\repositories\\video_deconstruction_repository.py", "source_location": "L28"}, {"id": "video_deconstruction_repository_videodeconstructionrepository_get_stage_run", "label": ".get_stage_run()", "file_type": "code", "source_file": "G:\\AI\\TK-OPS-ASSISTANT-V3\\apps\\py-runtime\\src\\repositories\\video_deconstruction_repository.py", "source_location": "L37"}, {"id": "video_deconstruction_repository_videodeconstructionrepository_upsert_stage_run", "label": ".upsert_stage_run()", "file_type": "code", "source_file": "G:\\AI\\TK-OPS-ASSISTANT-V3\\apps\\py-runtime\\src\\repositories\\video_deconstruction_repository.py", "source_location": "L45"}, {"id": "video_deconstruction_repository_videodeconstructionrepository_to_stored", "label": "._to_stored()", "file_type": "code", "source_file": "G:\\AI\\TK-OPS-ASSISTANT-V3\\apps\\py-runtime\\src\\repositories\\video_deconstruction_repository.py", "source_location": "L81"}, {"id": "video_deconstruction_repository_utc_now", "label": "_utc_now()", "file_type": "code", "source_file": "G:\\AI\\TK-OPS-ASSISTANT-V3\\apps\\py-runtime\\src\\repositories\\video_deconstruction_repository.py", "source_location": "L94"}], "edges": [{"source": "g_ai_tk_ops_assistant_v3_apps_py_runtime_src_repositories_video_deconstruction_repository_py", "target": "dataclasses", "relation": "imports_from", "confidence": "EXTRACTED", "source_file": "G:\\AI\\TK-OPS-ASSISTANT-V3\\apps\\py-runtime\\src\\repositories\\video_deconstruction_repository.py", "source_location": "L3", "weight": 1.0}, {"source": "g_ai_tk_ops_assistant_v3_apps_py_runtime_src_repositories_video_deconstruction_repository_py", "target": "datetime", "relation": "imports_from", "confidence": "EXTRACTED", "source_file": "G:\\AI\\TK-OPS-ASSISTANT-V3\\apps\\py-runtime\\src\\repositories\\video_deconstruction_repository.py", "source_location": "L4", "weight": 1.0}, {"source": "g_ai_tk_ops_assistant_v3_apps_py_runtime_src_repositories_video_deconstruction_repository_py", "target": "sqlalchemy", "relation": "imports_from", "confidence": "EXTRACTED", "source_file": "G:\\AI\\TK-OPS-ASSISTANT-V3\\apps\\py-runtime\\src\\repositories\\video_deconstruction_repository.py", "source_location": "L6", "weight": 1.0}, {"source": "g_ai_tk_ops_assistant_v3_apps_py_runtime_src_repositories_video_deconstruction_repository_py", "target": "sqlalchemy_orm", "relation": "imports_from", "confidence": "EXTRACTED", "source_file": "G:\\AI\\TK-OPS-ASSISTANT-V3\\apps\\py-runtime\\src\\repositories\\video_deconstruction_repository.py", "source_location": "L7", "weight": 1.0}, {"source": "g_ai_tk_ops_assistant_v3_apps_py_runtime_src_repositories_video_deconstruction_repository_py", "target": "domain_models", "relation": "imports_from", "confidence": "EXTRACTED", "source_file": "G:\\AI\\TK-OPS-ASSISTANT-V3\\apps\\py-runtime\\src\\repositories\\video_deconstruction_repository.py", "source_location": "L9", "weight": 1.0}, {"source": "g_ai_tk_ops_assistant_v3_apps_py_runtime_src_repositories_video_deconstruction_repository_py", "target": "video_deconstruction_repository_storedvideostagerun", "relation": "contains", "confidence": "EXTRACTED", "source_file": "G:\\AI\\TK-OPS-ASSISTANT-V3\\apps\\py-runtime\\src\\repositories\\video_deconstruction_repository.py", "source_location": "L13", "weight": 1.0}, {"source": "g_ai_tk_ops_assistant_v3_apps_py_runtime_src_repositories_video_deconstruction_repository_py", "target": "video_deconstruction_repository_videodeconstructionrepository", "relation": "contains", "confidence": "EXTRACTED", "source_file": "G:\\AI\\TK-OPS-ASSISTANT-V3\\apps\\py-runtime\\src\\repositories\\video_deconstruction_repository.py", "source_location": "L24", "weight": 1.0}, {"source": "video_deconstruction_repository_videodeconstructionrepository", "target": "video_deconstruction_repository_videodeconstructionrepository_init", "relation": "method", "confidence": "EXTRACTED", "source_file": "G:\\AI\\TK-OPS-ASSISTANT-V3\\apps\\py-runtime\\src\\repositories\\video_deconstruction_repository.py", "source_location": "L25", "weight": 1.0}, {"source": "video_deconstruction_repository_videodeconstructionrepository", "target": "video_deconstruction_repository_videodeconstructionrepository_list_stage_runs", "relation": "method", "confidence": "EXTRACTED", "source_file": "G:\\AI\\TK-OPS-ASSISTANT-V3\\apps\\py-runtime\\src\\repositories\\video_deconstruction_repository.py", "source_location": "L28", "weight": 1.0}, {"source": "video_deconstruction_repository_videodeconstructionrepository", "target": "video_deconstruction_repository_videodeconstructionrepository_get_stage_run", "relation": "method", "confidence": "EXTRACTED", "source_file": "G:\\AI\\TK-OPS-ASSISTANT-V3\\apps\\py-runtime\\src\\repositories\\video_deconstruction_repository.py", "source_location": "L37", "weight": 1.0}, {"source": "video_deconstruction_repository_videodeconstructionrepository", "target": "video_deconstruction_repository_videodeconstructionrepository_upsert_stage_run", "relation": "method", "confidence": "EXTRACTED", "source_file": "G:\\AI\\TK-OPS-ASSISTANT-V3\\apps\\py-runtime\\src\\repositories\\video_deconstruction_repository.py", "source_location": "L45", "weight": 1.0}, {"source": "video_deconstruction_repository_videodeconstructionrepository", "target": "video_deconstruction_repository_videodeconstructionrepository_to_stored", "relation": "method", "confidence": "EXTRACTED", "source_file": "G:\\AI\\TK-OPS-ASSISTANT-V3\\apps\\py-runtime\\src\\repositories\\video_deconstruction_repository.py", "source_location": "L81", "weight": 1.0}, {"source": "g_ai_tk_ops_assistant_v3_apps_py_runtime_src_repositories_video_deconstruction_repository_py", "target": "video_deconstruction_repository_utc_now", "relation": "contains", "confidence": "EXTRACTED", "source_file": "G:\\AI\\TK-OPS-ASSISTANT-V3\\apps\\py-runtime\\src\\repositories\\video_deconstruction_repository.py", "source_location": "L94", "weight": 1.0}, {"source": "video_deconstruction_repository_videodeconstructionrepository_list_stage_runs", "target": "video_deconstruction_repository_videodeconstructionrepository_to_stored", "relation": "calls", "confidence": "EXTRACTED", "source_file": "G:\\AI\\TK-OPS-ASSISTANT-V3\\apps\\py-runtime\\src\\repositories\\video_deconstruction_repository.py", "source_location": "L35", "weight": 1.0}, {"source": "video_deconstruction_repository_videodeconstructionrepository_get_stage_run", "target": "video_deconstruction_repository_videodeconstructionrepository_to_stored", "relation": "calls", "confidence": "EXTRACTED", "source_file": "G:\\AI\\TK-OPS-ASSISTANT-V3\\apps\\py-runtime\\src\\repositories\\video_deconstruction_repository.py", "source_location": "L43", "weight": 1.0}, {"source": "video_deconstruction_repository_videodeconstructionrepository_upsert_stage_run", "target": "video_deconstruction_repository_utc_now", "relation": "calls", "confidence": "EXTRACTED", "source_file": "G:\\AI\\TK-OPS-ASSISTANT-V3\\apps\\py-runtime\\src\\repositories\\video_deconstruction_repository.py", "source_location": "L57", "weight": 1.0}, {"source": "video_deconstruction_repository_videodeconstructionrepository_upsert_stage_run", "target": "video_deconstruction_repository_videodeconstructionrepository_to_stored", "relation": "calls", "confidence": "EXTRACTED", "source_file": "G:\\AI\\TK-OPS-ASSISTANT-V3\\apps\\py-runtime\\src\\repositories\\video_deconstruction_repository.py", "source_location": "L79", "weight": 1.0}, {"source": "video_deconstruction_repository_videodeconstructionrepository_to_stored", "target": "video_deconstruction_repository_storedvideostagerun", "relation": "calls", "confidence": "EXTRACTED", "source_file": "G:\\AI\\TK-OPS-ASSISTANT-V3\\apps\\py-runtime\\src\\repositories\\video_deconstruction_repository.py", "source_location": "L82", "weight": 1.0}], "raw_calls": [{"caller_nid": "video_deconstruction_repository_videodeconstructionrepository_list_stage_runs", "callee": "_session_factory", "source_file": "G:\\AI\\TK-OPS-ASSISTANT-V3\\apps\\py-runtime\\src\\repositories\\video_deconstruction_repository.py", "source_location": "L29"}, {"caller_nid": "video_deconstruction_repository_videodeconstructionrepository_list_stage_runs", "callee": "all", "source_file": "G:\\AI\\TK-OPS-ASSISTANT-V3\\apps\\py-runtime\\src\\repositories\\video_deconstruction_repository.py", "source_location": "L30"}, {"caller_nid": "video_deconstruction_repository_videodeconstructionrepository_list_stage_runs", "callee": "scalars", "source_file": "G:\\AI\\TK-OPS-ASSISTANT-V3\\apps\\py-runtime\\src\\repositories\\video_deconstruction_repository.py", "source_location": "L30"}, {"caller_nid": "video_deconstruction_repository_videodeconstructionrepository_list_stage_runs", "callee": "order_by", "source_file": "G:\\AI\\TK-OPS-ASSISTANT-V3\\apps\\py-runtime\\src\\repositories\\video_deconstruction_repository.py", "source_location": "L31"}, {"caller_nid": "video_deconstruction_repository_videodeconstructionrepository_list_stage_runs", "callee": "where", "source_file": "G:\\AI\\TK-OPS-ASSISTANT-V3\\apps\\py-runtime\\src\\repositories\\video_deconstruction_repository.py", "source_location": "L31"}, {"caller_nid": "video_deconstruction_repository_videodeconstructionrepository_list_stage_runs", "callee": "select", "source_file": "G:\\AI\\TK-OPS-ASSISTANT-V3\\apps\\py-runtime\\src\\repositories\\video_deconstruction_repository.py", "source_location": "L31"}, {"caller_nid": "video_deconstruction_repository_videodeconstructionrepository_list_stage_runs", "callee": "asc", "source_file": "G:\\AI\\TK-OPS-ASSISTANT-V3\\apps\\py-runtime\\src\\repositories\\video_deconstruction_repository.py", "source_location": "L33"}, {"caller_nid": "video_deconstruction_repository_videodeconstructionrepository_get_stage_run", "callee": "_session_factory", "source_file": "G:\\AI\\TK-OPS-ASSISTANT-V3\\apps\\py-runtime\\src\\repositories\\video_deconstruction_repository.py", "source_location": "L38"}, {"caller_nid": "video_deconstruction_repository_videodeconstructionrepository_get_stage_run", "callee": "get", "source_file": "G:\\AI\\TK-OPS-ASSISTANT-V3\\apps\\py-runtime\\src\\repositories\\video_deconstruction_repository.py", "source_location": "L39"}, {"caller_nid": "video_deconstruction_repository_videodeconstructionrepository_get_stage_run", "callee": "expunge", "source_file": "G:\\AI\\TK-OPS-ASSISTANT-V3\\apps\\py-runtime\\src\\repositories\\video_deconstruction_repository.py", "source_location": "L42"}, {"caller_nid": "video_deconstruction_repository_videodeconstructionrepository_upsert_stage_run", "callee": "_session_factory", "source_file": "G:\\AI\\TK-OPS-ASSISTANT-V3\\apps\\py-runtime\\src\\repositories\\video_deconstruction_repository.py", "source_location": "L55"}, {"caller_nid": "video_deconstruction_repository_videodeconstructionrepository_upsert_stage_run", "callee": "get", "source_file": "G:\\AI\\TK-OPS-ASSISTANT-V3\\apps\\py-runtime\\src\\repositories\\video_deconstruction_repository.py", "source_location": "L56"}, {"caller_nid": "video_deconstruction_repository_videodeconstructionrepository_upsert_stage_run", "callee": "VideoStageRun", "source_file": "G:\\AI\\TK-OPS-ASSISTANT-V3\\apps\\py-runtime\\src\\repositories\\video_deconstruction_repository.py", "source_location": "L59"}, {"caller_nid": "video_deconstruction_repository_videodeconstructionrepository_upsert_stage_run", "callee": "add", "source_file": "G:\\AI\\TK-OPS-ASSISTANT-V3\\apps\\py-runtime\\src\\repositories\\video_deconstruction_repository.py", "source_location": "L69"}, {"caller_nid": "video_deconstruction_repository_videodeconstructionrepository_upsert_stage_run", "callee": "commit", "source_file": "G:\\AI\\TK-OPS-ASSISTANT-V3\\apps\\py-runtime\\src\\repositories\\video_deconstruction_repository.py", "source_location": "L76"}, {"caller_nid": "video_deconstruction_repository_videodeconstructionrepository_upsert_stage_run", "callee": "refresh", "source_file": "G:\\AI\\TK-OPS-ASSISTANT-V3\\apps\\py-runtime\\src\\repositories\\video_deconstruction_repository.py", "source_location": "L77"}, {"caller_nid": "video_deconstruction_repository_videodeconstructionrepository_upsert_stage_run", "callee": "expunge", "source_file": "G:\\AI\\TK-OPS-ASSISTANT-V3\\apps\\py-runtime\\src\\repositories\\video_deconstruction_repository.py", "source_location": "L78"}, {"caller_nid": "video_deconstruction_repository_utc_now", "callee": "replace", "source_file": "G:\\AI\\TK-OPS-ASSISTANT-V3\\apps\\py-runtime\\src\\repositories\\video_deconstruction_repository.py", "source_location": "L95"}, {"caller_nid": "video_deconstruction_repository_utc_now", "callee": "isoformat", "source_file": "G:\\AI\\TK-OPS-ASSISTANT-V3\\apps\\py-runtime\\src\\repositories\\video_deconstruction_repository.py", "source_location": "L95"}, {"caller_nid": "video_deconstruction_repository_utc_now", "callee": "now", "source_file": "G:\\AI\\TK-OPS-ASSISTANT-V3\\apps\\py-runtime\\src\\repositories\\video_deconstruction_repository.py", "source_location": "L95"}]}