{"nodes": [{"id": "c_users_wz_desktop_py_tk_ops_assistant_v3_apps_desktop_src_stores_video_import_ts", "label": "video-import.ts", "file_type": "code", "source_file": "C:\\Users\\wz\\Desktop\\py\\TK-OPS-ASSISTANT-v3\\apps\\desktop\\src\\stores\\video-import.ts", "source_location": "L1"}, {"id": "video_import_shouldrefreshvideolist", "label": "shouldRefreshVideoList()", "file_type": "code", "source_file": "C:\\Users\\wz\\Desktop\\py\\TK-OPS-ASSISTANT-v3\\apps\\desktop\\src\\stores\\video-import.ts", "source_location": "L179"}, {"id": "video_import_derivetaskinfofromvideoevent", "label": "deriveTaskInfoFromVideoEvent()", "file_type": "code", "source_file": "C:\\Users\\wz\\Desktop\\py\\TK-OPS-ASSISTANT-v3\\apps\\desktop\\src\\stores\\video-import.ts", "source_location": "L190"}, {"id": "video_import_derivestagemessage", "label": "deriveStageMessage()", "file_type": "code", "source_file": "C:\\Users\\wz\\Desktop\\py\\TK-OPS-ASSISTANT-v3\\apps\\desktop\\src\\stores\\video-import.ts", "source_location": "L247"}, {"id": "video_import_stagelabel", "label": "stageLabel()", "file_type": "code", "source_file": "C:\\Users\\wz\\Desktop\\py\\TK-OPS-ASSISTANT-v3\\apps\\desktop\\src\\stores\\video-import.ts", "source_location": "L265"}], "edges": [{"source": "c_users_wz_desktop_py_tk_ops_assistant_v3_apps_desktop_src_stores_video_import_ts", "target": "pinia", "relation": "imports_from", "confidence": "EXTRACTED", "source_file": "C:\\Users\\wz\\Desktop\\py\\TK-OPS-ASSISTANT-v3\\apps\\desktop\\src\\stores\\video-import.ts", "source_location": "L1", "weight": 1.0}, {"source": "c_users_wz_desktop_py_tk_ops_assistant_v3_apps_desktop_src_stores_video_import_ts", "target": "runtime_client", "relation": "imports_from", "confidence": "EXTRACTED", "source_file": "C:\\Users\\wz\\Desktop\\py\\TK-OPS-ASSISTANT-v3\\apps\\desktop\\src\\stores\\video-import.ts", "source_location": "L3", "weight": 1.0}, {"source": "c_users_wz_desktop_py_tk_ops_assistant_v3_apps_desktop_src_stores_video_import_ts", "target": "task_bus", "relation": "imports_from", "confidence": "EXTRACTED", "source_file": "C:\\Users\\wz\\Desktop\\py\\TK-OPS-ASSISTANT-v3\\apps\\desktop\\src\\stores\\video-import.ts", "source_location": "L10", "weight": 1.0}, {"source": "c_users_wz_desktop_py_tk_ops_assistant_v3_apps_desktop_src_stores_video_import_ts", "target": "project", "relation": "imports_from", "confidence": "EXTRACTED", "source_file": "C:\\Users\\wz\\Desktop\\py\\TK-OPS-ASSISTANT-v3\\apps\\desktop\\src\\stores\\video-import.ts", "source_location": "L11", "weight": 1.0}, {"source": "c_users_wz_desktop_py_tk_ops_assistant_v3_apps_desktop_src_stores_video_import_ts", "target": "task_events", "relation": "imports_from", "confidence": "EXTRACTED", "source_file": "C:\\Users\\wz\\Desktop\\py\\TK-OPS-ASSISTANT-v3\\apps\\desktop\\src\\stores\\video-import.ts", "source_location": "L12", "weight": 1.0}, {"source": "c_users_wz_desktop_py_tk_ops_assistant_v3_apps_desktop_src_stores_video_import_ts", "target": "runtime", "relation": "imports_from", "confidence": "EXTRACTED", "source_file": "C:\\Users\\wz\\Desktop\\py\\TK-OPS-ASSISTANT-v3\\apps\\desktop\\src\\stores\\video-import.ts", "source_location": "L13", "weight": 1.0}, {"source": "c_users_wz_desktop_py_tk_ops_assistant_v3_apps_desktop_src_stores_video_import_ts", "target": "video", "relation": "imports_from", "confidence": "EXTRACTED", "source_file": "C:\\Users\\wz\\Desktop\\py\\TK-OPS-ASSISTANT-v3\\apps\\desktop\\src\\stores\\video-import.ts", "source_location": "L14", "weight": 1.0}, {"source": "c_users_wz_desktop_py_tk_ops_assistant_v3_apps_desktop_src_stores_video_import_ts", "target": "video_import_shouldrefreshvideolist", "relation": "contains", "confidence": "EXTRACTED", "source_file": "C:\\Users\\wz\\Desktop\\py\\TK-OPS-ASSISTANT-v3\\apps\\desktop\\src\\stores\\video-import.ts", "source_location": "L179", "weight": 1.0}, {"source": "c_users_wz_desktop_py_tk_ops_assistant_v3_apps_desktop_src_stores_video_import_ts", "target": "video_import_derivetaskinfofromvideoevent", "relation": "contains", "confidence": "EXTRACTED", "source_file": "C:\\Users\\wz\\Desktop\\py\\TK-OPS-ASSISTANT-v3\\apps\\desktop\\src\\stores\\video-import.ts", "source_location": "L190", "weight": 1.0}, {"source": "c_users_wz_desktop_py_tk_ops_assistant_v3_apps_desktop_src_stores_video_import_ts", "target": "video_import_derivestagemessage", "relation": "contains", "confidence": "EXTRACTED", "source_file": "C:\\Users\\wz\\Desktop\\py\\TK-OPS-ASSISTANT-v3\\apps\\desktop\\src\\stores\\video-import.ts", "source_location": "L247", "weight": 1.0}, {"source": "c_users_wz_desktop_py_tk_ops_assistant_v3_apps_desktop_src_stores_video_import_ts", "target": "video_import_stagelabel", "relation": "contains", "confidence": "EXTRACTED", "source_file": "C:\\Users\\wz\\Desktop\\py\\TK-OPS-ASSISTANT-v3\\apps\\desktop\\src\\stores\\video-import.ts", "source_location": "L265", "weight": 1.0}, {"source": "video_import_derivetaskinfofromvideoevent", "target": "video_import_derivestagemessage", "relation": "calls", "confidence": "EXTRACTED", "source_file": "C:\\Users\\wz\\Desktop\\py\\TK-OPS-ASSISTANT-v3\\apps\\desktop\\src\\stores\\video-import.ts", "source_location": "L211", "weight": 1.0}, {"source": "video_import_derivestagemessage", "target": "video_import_stagelabel", "relation": "calls", "confidence": "EXTRACTED", "source_file": "C:\\Users\\wz\\Desktop\\py\\TK-OPS-ASSISTANT-v3\\apps\\desktop\\src\\stores\\video-import.ts", "source_location": "L252", "weight": 1.0}], "raw_calls": [{"caller_nid": "video_import_shouldrefreshvideolist", "callee": "includes", "source_file": "C:\\Users\\wz\\Desktop\\py\\TK-OPS-ASSISTANT-v3\\apps\\desktop\\src\\stores\\video-import.ts", "source_location": "L182"}, {"caller_nid": "video_import_shouldrefreshvideolist", "callee": "includes", "source_file": "C:\\Users\\wz\\Desktop\\py\\TK-OPS-ASSISTANT-v3\\apps\\desktop\\src\\stores\\video-import.ts", "source_location": "L187"}, {"caller_nid": "video_import_derivetaskinfofromvideoevent", "callee": "includes", "source_file": "C:\\Users\\wz\\Desktop\\py\\TK-OPS-ASSISTANT-v3\\apps\\desktop\\src\\stores\\video-import.ts", "source_location": "L199"}, {"caller_nid": "video_import_derivetaskinfofromvideoevent", "callee": "toISOString", "source_file": "C:\\Users\\wz\\Desktop\\py\\TK-OPS-ASSISTANT-v3\\apps\\desktop\\src\\stores\\video-import.ts", "source_location": "L224"}]}