{"nodes": [{"id": "c_users_wz_desktop_py_tk_ops_assistant_v3_apps_desktop_src_pages_assets_assetlibrarypage_vue", "label": "AssetLibraryPage.vue", "file_type": "code", "source_file": "C:\\Users\\wz\\Desktop\\py\\TK-OPS-ASSISTANT-v3\\apps\\desktop\\src\\pages\\assets\\AssetLibraryPage.vue", "source_location": "L1"}, {"id": "assetlibrarypage_typelabel", "label": "typeLabel()", "file_type": "code", "source_file": "C:\\Users\\wz\\Desktop\\py\\TK-OPS-ASSISTANT-v3\\apps\\desktop\\src\\pages\\assets\\AssetLibraryPage.vue", "source_location": "L116"}, {"id": "assetlibrarypage_assetstatus", "label": "assetStatus()", "file_type": "code", "source_file": "C:\\Users\\wz\\Desktop\\py\\TK-OPS-ASSISTANT-v3\\apps\\desktop\\src\\pages\\assets\\AssetLibraryPage.vue", "source_location": "L237"}, {"id": "assetlibrarypage_handlereload", "label": "handleReload()", "file_type": "code", "source_file": "C:\\Users\\wz\\Desktop\\py\\TK-OPS-ASSISTANT-v3\\apps\\desktop\\src\\pages\\assets\\AssetLibraryPage.vue", "source_location": "L285"}, {"id": "assetlibrarypage_handlesearch", "label": "handleSearch()", "file_type": "code", "source_file": "C:\\Users\\wz\\Desktop\\py\\TK-OPS-ASSISTANT-v3\\apps\\desktop\\src\\pages\\assets\\AssetLibraryPage.vue", "source_location": "L286"}, {"id": "assetlibrarypage_handlefiltertype", "label": "handleFilterType()", "file_type": "code", "source_file": "C:\\Users\\wz\\Desktop\\py\\TK-OPS-ASSISTANT-v3\\apps\\desktop\\src\\pages\\assets\\AssetLibraryPage.vue", "source_location": "L287"}, {"id": "assetlibrarypage_handlesort", "label": "handleSort()", "file_type": "code", "source_file": "C:\\Users\\wz\\Desktop\\py\\TK-OPS-ASSISTANT-v3\\apps\\desktop\\src\\pages\\assets\\AssetLibraryPage.vue", "source_location": "L288"}, {"id": "assetlibrarypage_handledragover", "label": "handleDragOver()", "file_type": "code", "source_file": "C:\\Users\\wz\\Desktop\\py\\TK-OPS-ASSISTANT-v3\\apps\\desktop\\src\\pages\\assets\\AssetLibraryPage.vue", "source_location": "L290"}, {"id": "assetlibrarypage_handledragleave", "label": "handleDragLeave()", "file_type": "code", "source_file": "C:\\Users\\wz\\Desktop\\py\\TK-OPS-ASSISTANT-v3\\apps\\desktop\\src\\pages\\assets\\AssetLibraryPage.vue", "source_location": "L296"}, {"id": "assetlibrarypage_handleupload", "label": "handleUpload()", "file_type": "code", "source_file": "C:\\Users\\wz\\Desktop\\py\\TK-OPS-ASSISTANT-v3\\apps\\desktop\\src\\pages\\assets\\AssetLibraryPage.vue", "source_location": "L301"}, {"id": "assetlibrarypage_handledrop", "label": "handleDrop()", "file_type": "code", "source_file": "C:\\Users\\wz\\Desktop\\py\\TK-OPS-ASSISTANT-v3\\apps\\desktop\\src\\pages\\assets\\AssetLibraryPage.vue", "source_location": "L312"}, {"id": "assetlibrarypage_importfrompaths", "label": "importFromPaths()", "file_type": "code", "source_file": "C:\\Users\\wz\\Desktop\\py\\TK-OPS-ASSISTANT-v3\\apps\\desktop\\src\\pages\\assets\\AssetLibraryPage.vue", "source_location": "L330"}, {"id": "assetlibrarypage_clearselection", "label": "clearSelection()", "file_type": "code", "source_file": "C:\\Users\\wz\\Desktop\\py\\TK-OPS-ASSISTANT-v3\\apps\\desktop\\src\\pages\\assets\\AssetLibraryPage.vue", "source_location": "L401"}, {"id": "assetlibrarypage_openselectedassetdetail", "label": "openSelectedAssetDetail()", "file_type": "code", "source_file": "C:\\Users\\wz\\Desktop\\py\\TK-OPS-ASSISTANT-v3\\apps\\desktop\\src\\pages\\assets\\AssetLibraryPage.vue", "source_location": "L407"}, {"id": "assetlibrarypage_buildassetdetailcontext", "label": "buildAssetDetailContext()", "file_type": "code", "source_file": "C:\\Users\\wz\\Desktop\\py\\TK-OPS-ASSISTANT-v3\\apps\\desktop\\src\\pages\\assets\\AssetLibraryPage.vue", "source_location": "L413"}, {"id": "assetlibrarypage_inferassettype", "label": "inferAssetType()", "file_type": "code", "source_file": "C:\\Users\\wz\\Desktop\\py\\TK-OPS-ASSISTANT-v3\\apps\\desktop\\src\\pages\\assets\\AssetLibraryPage.vue", "source_location": "L461"}, {"id": "assetlibrarypage_counttransferfiles", "label": "countTransferFiles()", "file_type": "code", "source_file": "C:\\Users\\wz\\Desktop\\py\\TK-OPS-ASSISTANT-v3\\apps\\desktop\\src\\pages\\assets\\AssetLibraryPage.vue", "source_location": "L472"}, {"id": "assetlibrarypage_formatsize", "label": "formatSize()", "file_type": "code", "source_file": "C:\\Users\\wz\\Desktop\\py\\TK-OPS-ASSISTANT-v3\\apps\\desktop\\src\\pages\\assets\\AssetLibraryPage.vue", "source_location": "L483"}, {"id": "assetlibrarypage_formatduration", "label": "formatDuration()", "file_type": "code", "source_file": "C:\\Users\\wz\\Desktop\\py\\TK-OPS-ASSISTANT-v3\\apps\\desktop\\src\\pages\\assets\\AssetLibraryPage.vue", "source_location": "L492"}, {"id": "assetlibrarypage_formatshanghaidatetime", "label": "formatShanghaiDateTime()", "file_type": "code", "source_file": "C:\\Users\\wz\\Desktop\\py\\TK-OPS-ASSISTANT-v3\\apps\\desktop\\src\\pages\\assets\\AssetLibraryPage.vue", "source_location": "L500"}, {"id": "assetlibrarypage_totime", "label": "toTime()", "file_type": "code", "source_file": "C:\\Users\\wz\\Desktop\\py\\TK-OPS-ASSISTANT-v3\\apps\\desktop\\src\\pages\\assets\\AssetLibraryPage.vue", "source_location": "L510"}], "edges": [{"source": "c_users_wz_desktop_py_tk_ops_assistant_v3_apps_desktop_src_pages_assets_assetlibrarypage_vue", "target": "assetlibrarypage_typelabel", "relation": "contains", "confidence": "EXTRACTED", "source_file": "C:\\Users\\wz\\Desktop\\py\\TK-OPS-ASSISTANT-v3\\apps\\desktop\\src\\pages\\assets\\AssetLibraryPage.vue", "source_location": "L116", "weight": 1.0}, {"source": "c_users_wz_desktop_py_tk_ops_assistant_v3_apps_desktop_src_pages_assets_assetlibrarypage_vue", "target": "assetlibrarypage_assetstatus", "relation": "contains", "confidence": "EXTRACTED", "source_file": "C:\\Users\\wz\\Desktop\\py\\TK-OPS-ASSISTANT-v3\\apps\\desktop\\src\\pages\\assets\\AssetLibraryPage.vue", "source_location": "L237", "weight": 1.0}, {"source": "c_users_wz_desktop_py_tk_ops_assistant_v3_apps_desktop_src_pages_assets_assetlibrarypage_vue", "target": "assetlibrarypage_handlereload", "relation": "contains", "confidence": "EXTRACTED", "source_file": "C:\\Users\\wz\\Desktop\\py\\TK-OPS-ASSISTANT-v3\\apps\\desktop\\src\\pages\\assets\\AssetLibraryPage.vue", "source_location": "L285", "weight": 1.0}, {"source": "c_users_wz_desktop_py_tk_ops_assistant_v3_apps_desktop_src_pages_assets_assetlibrarypage_vue", "target": "assetlibrarypage_handlesearch", "relation": "contains", "confidence": "EXTRACTED", "source_file": "C:\\Users\\wz\\Desktop\\py\\TK-OPS-ASSISTANT-v3\\apps\\desktop\\src\\pages\\assets\\AssetLibraryPage.vue", "source_location": "L286", "weight": 1.0}, {"source": "c_users_wz_desktop_py_tk_ops_assistant_v3_apps_desktop_src_pages_assets_assetlibrarypage_vue", "target": "assetlibrarypage_handlefiltertype", "relation": "contains", "confidence": "EXTRACTED", "source_file": "C:\\Users\\wz\\Desktop\\py\\TK-OPS-ASSISTANT-v3\\apps\\desktop\\src\\pages\\assets\\AssetLibraryPage.vue", "source_location": "L287", "weight": 1.0}, {"source": "c_users_wz_desktop_py_tk_ops_assistant_v3_apps_desktop_src_pages_assets_assetlibrarypage_vue", "target": "assetlibrarypage_handlesort", "relation": "contains", "confidence": "EXTRACTED", "source_file": "C:\\Users\\wz\\Desktop\\py\\TK-OPS-ASSISTANT-v3\\apps\\desktop\\src\\pages\\assets\\AssetLibraryPage.vue", "source_location": "L288", "weight": 1.0}, {"source": "c_users_wz_desktop_py_tk_ops_assistant_v3_apps_desktop_src_pages_assets_assetlibrarypage_vue", "target": "assetlibrarypage_handledragover", "relation": "contains", "confidence": "EXTRACTED", "source_file": "C:\\Users\\wz\\Desktop\\py\\TK-OPS-ASSISTANT-v3\\apps\\desktop\\src\\pages\\assets\\AssetLibraryPage.vue", "source_location": "L290", "weight": 1.0}, {"source": "c_users_wz_desktop_py_tk_ops_assistant_v3_apps_desktop_src_pages_assets_assetlibrarypage_vue", "target": "assetlibrarypage_handledragleave", "relation": "contains", "confidence": "EXTRACTED", "source_file": "C:\\Users\\wz\\Desktop\\py\\TK-OPS-ASSISTANT-v3\\apps\\desktop\\src\\pages\\assets\\AssetLibraryPage.vue", "source_location": "L296", "weight": 1.0}, {"source": "c_users_wz_desktop_py_tk_ops_assistant_v3_apps_desktop_src_pages_assets_assetlibrarypage_vue", "target": "assetlibrarypage_handleupload", "relation": "contains", "confidence": "EXTRACTED", "source_file": "C:\\Users\\wz\\Desktop\\py\\TK-OPS-ASSISTANT-v3\\apps\\desktop\\src\\pages\\assets\\AssetLibraryPage.vue", "source_location": "L301", "weight": 1.0}, {"source": "c_users_wz_desktop_py_tk_ops_assistant_v3_apps_desktop_src_pages_assets_assetlibrarypage_vue", "target": "assetlibrarypage_handledrop", "relation": "contains", "confidence": "EXTRACTED", "source_file": "C:\\Users\\wz\\Desktop\\py\\TK-OPS-ASSISTANT-v3\\apps\\desktop\\src\\pages\\assets\\AssetLibraryPage.vue", "source_location": "L312", "weight": 1.0}, {"source": "c_users_wz_desktop_py_tk_ops_assistant_v3_apps_desktop_src_pages_assets_assetlibrarypage_vue", "target": "assetlibrarypage_importfrompaths", "relation": "contains", "confidence": "EXTRACTED", "source_file": "C:\\Users\\wz\\Desktop\\py\\TK-OPS-ASSISTANT-v3\\apps\\desktop\\src\\pages\\assets\\AssetLibraryPage.vue", "source_location": "L330", "weight": 1.0}, {"source": "c_users_wz_desktop_py_tk_ops_assistant_v3_apps_desktop_src_pages_assets_assetlibrarypage_vue", "target": "assetlibrarypage_clearselection", "relation": "contains", "confidence": "EXTRACTED", "source_file": "C:\\Users\\wz\\Desktop\\py\\TK-OPS-ASSISTANT-v3\\apps\\desktop\\src\\pages\\assets\\AssetLibraryPage.vue", "source_location": "L401", "weight": 1.0}, {"source": "c_users_wz_desktop_py_tk_ops_assistant_v3_apps_desktop_src_pages_assets_assetlibrarypage_vue", "target": "assetlibrarypage_openselectedassetdetail", "relation": "contains", "confidence": "EXTRACTED", "source_file": "C:\\Users\\wz\\Desktop\\py\\TK-OPS-ASSISTANT-v3\\apps\\desktop\\src\\pages\\assets\\AssetLibraryPage.vue", "source_location": "L407", "weight": 1.0}, {"source": "c_users_wz_desktop_py_tk_ops_assistant_v3_apps_desktop_src_pages_assets_assetlibrarypage_vue", "target": "assetlibrarypage_buildassetdetailcontext", "relation": "contains", "confidence": "EXTRACTED", "source_file": "C:\\Users\\wz\\Desktop\\py\\TK-OPS-ASSISTANT-v3\\apps\\desktop\\src\\pages\\assets\\AssetLibraryPage.vue", "source_location": "L413", "weight": 1.0}, {"source": "c_users_wz_desktop_py_tk_ops_assistant_v3_apps_desktop_src_pages_assets_assetlibrarypage_vue", "target": "assetlibrarypage_inferassettype", "relation": "contains", "confidence": "EXTRACTED", "source_file": "C:\\Users\\wz\\Desktop\\py\\TK-OPS-ASSISTANT-v3\\apps\\desktop\\src\\pages\\assets\\AssetLibraryPage.vue", "source_location": "L461", "weight": 1.0}, {"source": "c_users_wz_desktop_py_tk_ops_assistant_v3_apps_desktop_src_pages_assets_assetlibrarypage_vue", "target": "assetlibrarypage_counttransferfiles", "relation": "contains", "confidence": "EXTRACTED", "source_file": "C:\\Users\\wz\\Desktop\\py\\TK-OPS-ASSISTANT-v3\\apps\\desktop\\src\\pages\\assets\\AssetLibraryPage.vue", "source_location": "L472", "weight": 1.0}, {"source": "c_users_wz_desktop_py_tk_ops_assistant_v3_apps_desktop_src_pages_assets_assetlibrarypage_vue", "target": "assetlibrarypage_typelabel", "relation": "contains", "confidence": "EXTRACTED", "source_file": "C:\\Users\\wz\\Desktop\\py\\TK-OPS-ASSISTANT-v3\\apps\\desktop\\src\\pages\\assets\\AssetLibraryPage.vue", "source_location": "L478", "weight": 1.0}, {"source": "c_users_wz_desktop_py_tk_ops_assistant_v3_apps_desktop_src_pages_assets_assetlibrarypage_vue", "target": "assetlibrarypage_formatsize", "relation": "contains", "confidence": "EXTRACTED", "source_file": "C:\\Users\\wz\\Desktop\\py\\TK-OPS-ASSISTANT-v3\\apps\\desktop\\src\\pages\\assets\\AssetLibraryPage.vue", "source_location": "L483", "weight": 1.0}, {"source": "c_users_wz_desktop_py_tk_ops_assistant_v3_apps_desktop_src_pages_assets_assetlibrarypage_vue", "target": "assetlibrarypage_formatduration", "relation": "contains", "confidence": "EXTRACTED", "source_file": "C:\\Users\\wz\\Desktop\\py\\TK-OPS-ASSISTANT-v3\\apps\\desktop\\src\\pages\\assets\\AssetLibraryPage.vue", "source_location": "L492", "weight": 1.0}, {"source": "c_users_wz_desktop_py_tk_ops_assistant_v3_apps_desktop_src_pages_assets_assetlibrarypage_vue", "target": "assetlibrarypage_formatshanghaidatetime", "relation": "contains", "confidence": "EXTRACTED", "source_file": "C:\\Users\\wz\\Desktop\\py\\TK-OPS-ASSISTANT-v3\\apps\\desktop\\src\\pages\\assets\\AssetLibraryPage.vue", "source_location": "L500", "weight": 1.0}, {"source": "c_users_wz_desktop_py_tk_ops_assistant_v3_apps_desktop_src_pages_assets_assetlibrarypage_vue", "target": "assetlibrarypage_totime", "relation": "contains", "confidence": "EXTRACTED", "source_file": "C:\\Users\\wz\\Desktop\\py\\TK-OPS-ASSISTANT-v3\\apps\\desktop\\src\\pages\\assets\\AssetLibraryPage.vue", "source_location": "L510", "weight": 1.0}, {"source": "assetlibrarypage_handledragover", "target": "assetlibrarypage_counttransferfiles", "relation": "calls", "confidence": "EXTRACTED", "source_file": "C:\\Users\\wz\\Desktop\\py\\TK-OPS-ASSISTANT-v3\\apps\\desktop\\src\\pages\\assets\\AssetLibraryPage.vue", "source_location": "L293", "weight": 1.0}, {"source": "assetlibrarypage_handleupload", "target": "assetlibrarypage_importfrompaths", "relation": "calls", "confidence": "EXTRACTED", "source_file": "C:\\Users\\wz\\Desktop\\py\\TK-OPS-ASSISTANT-v3\\apps\\desktop\\src\\pages\\assets\\AssetLibraryPage.vue", "source_location": "L309", "weight": 1.0}, {"source": "assetlibrarypage_handledrop", "target": "assetlibrarypage_importfrompaths", "relation": "calls", "confidence": "EXTRACTED", "source_file": "C:\\Users\\wz\\Desktop\\py\\TK-OPS-ASSISTANT-v3\\apps\\desktop\\src\\pages\\assets\\AssetLibraryPage.vue", "source_location": "L327", "weight": 1.0}, {"source": "assetlibrarypage_importfrompaths", "target": "assetlibrarypage_inferassettype", "relation": "calls", "confidence": "EXTRACTED", "source_file": "C:\\Users\\wz\\Desktop\\py\\TK-OPS-ASSISTANT-v3\\apps\\desktop\\src\\pages\\assets\\AssetLibraryPage.vue", "source_location": "L347", "weight": 1.0}, {"source": "assetlibrarypage_importfrompaths", "target": "assetlibrarypage_buildassetdetailcontext", "relation": "calls", "confidence": "EXTRACTED", "source_file": "C:\\Users\\wz\\Desktop\\py\\TK-OPS-ASSISTANT-v3\\apps\\desktop\\src\\pages\\assets\\AssetLibraryPage.vue", "source_location": "L361", "weight": 1.0}, {"source": "assetlibrarypage_openselectedassetdetail", "target": "assetlibrarypage_buildassetdetailcontext", "relation": "calls", "confidence": "EXTRACTED", "source_file": "C:\\Users\\wz\\Desktop\\py\\TK-OPS-ASSISTANT-v3\\apps\\desktop\\src\\pages\\assets\\AssetLibraryPage.vue", "source_location": "L410", "weight": 1.0}, {"source": "assetlibrarypage_buildassetdetailcontext", "target": "assetlibrarypage_typelabel", "relation": "calls", "confidence": "EXTRACTED", "source_file": "C:\\Users\\wz\\Desktop\\py\\TK-OPS-ASSISTANT-v3\\apps\\desktop\\src\\pages\\assets\\AssetLibraryPage.vue", "source_location": "L420", "weight": 1.0}, {"source": "assetlibrarypage_buildassetdetailcontext", "target": "assetlibrarypage_formatsize", "relation": "calls", "confidence": "EXTRACTED", "source_file": "C:\\Users\\wz\\Desktop\\py\\TK-OPS-ASSISTANT-v3\\apps\\desktop\\src\\pages\\assets\\AssetLibraryPage.vue", "source_location": "L422", "weight": 1.0}, {"source": "assetlibrarypage_buildassetdetailcontext", "target": "assetlibrarypage_formatduration", "relation": "calls", "confidence": "EXTRACTED", "source_file": "C:\\Users\\wz\\Desktop\\py\\TK-OPS-ASSISTANT-v3\\apps\\desktop\\src\\pages\\assets\\AssetLibraryPage.vue", "source_location": "L434", "weight": 1.0}, {"source": "assetlibrarypage_buildassetdetailcontext", "target": "assetlibrarypage_formatshanghaidatetime", "relation": "calls", "confidence": "EXTRACTED", "source_file": "C:\\Users\\wz\\Desktop\\py\\TK-OPS-ASSISTANT-v3\\apps\\desktop\\src\\pages\\assets\\AssetLibraryPage.vue", "source_location": "L435", "weight": 1.0}], "raw_calls": [{"caller_nid": "assetlibrarypage_handlereload", "callee": "load", "source_file": "C:\\Users\\wz\\Desktop\\py\\TK-OPS-ASSISTANT-v3\\apps\\desktop\\src\\pages\\assets\\AssetLibraryPage.vue", "source_location": "L285"}, {"caller_nid": "assetlibrarypage_handlesearch", "callee": "setSearchQuery", "source_file": "C:\\Users\\wz\\Desktop\\py\\TK-OPS-ASSISTANT-v3\\apps\\desktop\\src\\pages\\assets\\AssetLibraryPage.vue", "source_location": "L286"}, {"caller_nid": "assetlibrarypage_handlefiltertype", "callee": "setFilterType", "source_file": "C:\\Users\\wz\\Desktop\\py\\TK-OPS-ASSISTANT-v3\\apps\\desktop\\src\\pages\\assets\\AssetLibraryPage.vue", "source_location": "L287"}, {"caller_nid": "assetlibrarypage_handleupload", "callee": "pickAssetFilePaths", "source_file": "C:\\Users\\wz\\Desktop\\py\\TK-OPS-ASSISTANT-v3\\apps\\desktop\\src\\pages\\assets\\AssetLibraryPage.vue", "source_location": "L307"}, {"caller_nid": "assetlibrarypage_handledrop", "callee": "from", "source_file": "C:\\Users\\wz\\Desktop\\py\\TK-OPS-ASSISTANT-v3\\apps\\desktop\\src\\pages\\assets\\AssetLibraryPage.vue", "source_location": "L319"}, {"caller_nid": "assetlibrarypage_handledrop", "callee": "filter", "source_file": "C:\\Users\\wz\\Desktop\\py\\TK-OPS-ASSISTANT-v3\\apps\\desktop\\src\\pages\\assets\\AssetLibraryPage.vue", "source_location": "L322"}, {"caller_nid": "assetlibrarypage_handledrop", "callee": "map", "source_file": "C:\\Users\\wz\\Desktop\\py\\TK-OPS-ASSISTANT-v3\\apps\\desktop\\src\\pages\\assets\\AssetLibraryPage.vue", "source_location": "L322"}, {"caller_nid": "assetlibrarypage_importfrompaths", "callee": "filter", "source_file": "C:\\Users\\wz\\Desktop\\py\\TK-OPS-ASSISTANT-v3\\apps\\desktop\\src\\pages\\assets\\AssetLibraryPage.vue", "source_location": "L331"}, {"caller_nid": "assetlibrarypage_importfrompaths", "callee": "map", "source_file": "C:\\Users\\wz\\Desktop\\py\\TK-OPS-ASSISTANT-v3\\apps\\desktop\\src\\pages\\assets\\AssetLibraryPage.vue", "source_location": "L331"}, {"caller_nid": "assetlibrarypage_importfrompaths", "callee": "importLocalFile", "source_file": "C:\\Users\\wz\\Desktop\\py\\TK-OPS-ASSISTANT-v3\\apps\\desktop\\src\\pages\\assets\\AssetLibraryPage.vue", "source_location": "L347"}, {"caller_nid": "assetlibrarypage_importfrompaths", "callee": "push", "source_file": "C:\\Users\\wz\\Desktop\\py\\TK-OPS-ASSISTANT-v3\\apps\\desktop\\src\\pages\\assets\\AssetLibraryPage.vue", "source_location": "L348"}, {"caller_nid": "assetlibrarypage_importfrompaths", "callee": "push", "source_file": "C:\\Users\\wz\\Desktop\\py\\TK-OPS-ASSISTANT-v3\\apps\\desktop\\src\\pages\\assets\\AssetLibraryPage.vue", "source_location": "L351"}, {"caller_nid": "assetlibrarypage_importfrompaths", "callee": "select", "source_file": "C:\\Users\\wz\\Desktop\\py\\TK-OPS-ASSISTANT-v3\\apps\\desktop\\src\\pages\\assets\\AssetLibraryPage.vue", "source_location": "L360"}, {"caller_nid": "assetlibrarypage_importfrompaths", "callee": "openDetailWithContext", "source_file": "C:\\Users\\wz\\Desktop\\py\\TK-OPS-ASSISTANT-v3\\apps\\desktop\\src\\pages\\assets\\AssetLibraryPage.vue", "source_location": "L361"}, {"caller_nid": "assetlibrarypage_clearselection", "callee": "select", "source_file": "C:\\Users\\wz\\Desktop\\py\\TK-OPS-ASSISTANT-v3\\apps\\desktop\\src\\pages\\assets\\AssetLibraryPage.vue", "source_location": "L402"}, {"caller_nid": "assetlibrarypage_clearselection", "callee": "clearDetailContext", "source_file": "C:\\Users\\wz\\Desktop\\py\\TK-OPS-ASSISTANT-v3\\apps\\desktop\\src\\pages\\assets\\AssetLibraryPage.vue", "source_location": "L403"}, {"caller_nid": "assetlibrarypage_clearselection", "callee": "closeDetailPanel", "source_file": "C:\\Users\\wz\\Desktop\\py\\TK-OPS-ASSISTANT-v3\\apps\\desktop\\src\\pages\\assets\\AssetLibraryPage.vue", "source_location": "L404"}, {"caller_nid": "assetlibrarypage_openselectedassetdetail", "callee": "openDetailWithContext", "source_file": "C:\\Users\\wz\\Desktop\\py\\TK-OPS-ASSISTANT-v3\\apps\\desktop\\src\\pages\\assets\\AssetLibraryPage.vue", "source_location": "L410"}, {"caller_nid": "assetlibrarypage_buildassetdetailcontext", "callee": "parseTags", "source_file": "C:\\Users\\wz\\Desktop\\py\\TK-OPS-ASSISTANT-v3\\apps\\desktop\\src\\pages\\assets\\AssetLibraryPage.vue", "source_location": "L414"}, {"caller_nid": "assetlibrarypage_buildassetdetailcontext", "callee": "createRouteDetailContext", "source_file": "C:\\Users\\wz\\Desktop\\py\\TK-OPS-ASSISTANT-v3\\apps\\desktop\\src\\pages\\assets\\AssetLibraryPage.vue", "source_location": "L415"}, {"caller_nid": "assetlibrarypage_buildassetdetailcontext", "callee": "String", "source_file": "C:\\Users\\wz\\Desktop\\py\\TK-OPS-ASSISTANT-v3\\apps\\desktop\\src\\pages\\assets\\AssetLibraryPage.vue", "source_location": "L423"}, {"caller_nid": "assetlibrarypage_buildassetdetailcontext", "callee": "map", "source_file": "C:\\Users\\wz\\Desktop\\py\\TK-OPS-ASSISTANT-v3\\apps\\desktop\\src\\pages\\assets\\AssetLibraryPage.vue", "source_location": "L443"}, {"caller_nid": "assetlibrarypage_buildassetdetailcontext", "callee": "map", "source_file": "C:\\Users\\wz\\Desktop\\py\\TK-OPS-ASSISTANT-v3\\apps\\desktop\\src\\pages\\assets\\AssetLibraryPage.vue", "source_location": "L449"}, {"caller_nid": "assetlibrarypage_inferassettype", "callee": "startsWith", "source_file": "C:\\Users\\wz\\Desktop\\py\\TK-OPS-ASSISTANT-v3\\apps\\desktop\\src\\pages\\assets\\AssetLibraryPage.vue", "source_location": "L462"}, {"caller_nid": "assetlibrarypage_inferassettype", "callee": "startsWith", "source_file": "C:\\Users\\wz\\Desktop\\py\\TK-OPS-ASSISTANT-v3\\apps\\desktop\\src\\pages\\assets\\AssetLibraryPage.vue", "source_location": "L463"}, {"caller_nid": "assetlibrarypage_inferassettype", "callee": "startsWith", "source_file": "C:\\Users\\wz\\Desktop\\py\\TK-OPS-ASSISTANT-v3\\apps\\desktop\\src\\pages\\assets\\AssetLibraryPage.vue", "source_location": "L464"}, {"caller_nid": "assetlibrarypage_inferassettype", "callee": "toLowerCase", "source_file": "C:\\Users\\wz\\Desktop\\py\\TK-OPS-ASSISTANT-v3\\apps\\desktop\\src\\pages\\assets\\AssetLibraryPage.vue", "source_location": "L465"}, {"caller_nid": "assetlibrarypage_inferassettype", "callee": "test", "source_file": "C:\\Users\\wz\\Desktop\\py\\TK-OPS-ASSISTANT-v3\\apps\\desktop\\src\\pages\\assets\\AssetLibraryPage.vue", "source_location": "L466"}, {"caller_nid": "assetlibrarypage_inferassettype", "callee": "test", "source_file": "C:\\Users\\wz\\Desktop\\py\\TK-OPS-ASSISTANT-v3\\apps\\desktop\\src\\pages\\assets\\AssetLibraryPage.vue", "source_location": "L467"}, {"caller_nid": "assetlibrarypage_inferassettype", "callee": "test", "source_file": "C:\\Users\\wz\\Desktop\\py\\TK-OPS-ASSISTANT-v3\\apps\\desktop\\src\\pages\\assets\\AssetLibraryPage.vue", "source_location": "L468"}, {"caller_nid": "assetlibrarypage_counttransferfiles", "callee": "filter", "source_file": "C:\\Users\\wz\\Desktop\\py\\TK-OPS-ASSISTANT-v3\\apps\\desktop\\src\\pages\\assets\\AssetLibraryPage.vue", "source_location": "L474"}, {"caller_nid": "assetlibrarypage_counttransferfiles", "callee": "from", "source_file": "C:\\Users\\wz\\Desktop\\py\\TK-OPS-ASSISTANT-v3\\apps\\desktop\\src\\pages\\assets\\AssetLibraryPage.vue", "source_location": "L474"}, {"caller_nid": "assetlibrarypage_formatsize", "callee": "toFixed", "source_file": "C:\\Users\\wz\\Desktop\\py\\TK-OPS-ASSISTANT-v3\\apps\\desktop\\src\\pages\\assets\\AssetLibraryPage.vue", "source_location": "L489"}, {"caller_nid": "assetlibrarypage_formatduration", "callee": "max", "source_file": "C:\\Users\\wz\\Desktop\\py\\TK-OPS-ASSISTANT-v3\\apps\\desktop\\src\\pages\\assets\\AssetLibraryPage.vue", "source_location": "L494"}, {"caller_nid": "assetlibrarypage_formatduration", "callee": "round", "source_file": "C:\\Users\\wz\\Desktop\\py\\TK-OPS-ASSISTANT-v3\\apps\\desktop\\src\\pages\\assets\\AssetLibraryPage.vue", "source_location": "L494"}, {"caller_nid": "assetlibrarypage_formatduration", "callee": "floor", "source_file": "C:\\Users\\wz\\Desktop\\py\\TK-OPS-ASSISTANT-v3\\apps\\desktop\\src\\pages\\assets\\AssetLibraryPage.vue", "source_location": "L495"}, {"caller_nid": "assetlibrarypage_formatduration", "callee": "padStart", "source_file": "C:\\Users\\wz\\Desktop\\py\\TK-OPS-ASSISTANT-v3\\apps\\desktop\\src\\pages\\assets\\AssetLibraryPage.vue", "source_location": "L497"}, {"caller_nid": "assetlibrarypage_formatduration", "callee": "String", "source_file": "C:\\Users\\wz\\Desktop\\py\\TK-OPS-ASSISTANT-v3\\apps\\desktop\\src\\pages\\assets\\AssetLibraryPage.vue", "source_location": "L497"}, {"caller_nid": "assetlibrarypage_formatshanghaidatetime", "callee": "isNaN", "source_file": "C:\\Users\\wz\\Desktop\\py\\TK-OPS-ASSISTANT-v3\\apps\\desktop\\src\\pages\\assets\\AssetLibraryPage.vue", "source_location": "L502"}, {"caller_nid": "assetlibrarypage_formatshanghaidatetime", "callee": "getTime", "source_file": "C:\\Users\\wz\\Desktop\\py\\TK-OPS-ASSISTANT-v3\\apps\\desktop\\src\\pages\\assets\\AssetLibraryPage.vue", "source_location": "L502"}, {"caller_nid": "assetlibrarypage_formatshanghaidatetime", "callee": "formatToParts", "source_file": "C:\\Users\\wz\\Desktop\\py\\TK-OPS-ASSISTANT-v3\\apps\\desktop\\src\\pages\\assets\\AssetLibraryPage.vue", "source_location": "L503"}, {"caller_nid": "assetlibrarypage_formatshanghaidatetime", "callee": "part", "source_file": "C:\\Users\\wz\\Desktop\\py\\TK-OPS-ASSISTANT-v3\\apps\\desktop\\src\\pages\\assets\\AssetLibraryPage.vue", "source_location": "L507"}, {"caller_nid": "assetlibrarypage_formatshanghaidatetime", "callee": "part", "source_file": "C:\\Users\\wz\\Desktop\\py\\TK-OPS-ASSISTANT-v3\\apps\\desktop\\src\\pages\\assets\\AssetLibraryPage.vue", "source_location": "L507"}, {"caller_nid": "assetlibrarypage_formatshanghaidatetime", "callee": "part", "source_file": "C:\\Users\\wz\\Desktop\\py\\TK-OPS-ASSISTANT-v3\\apps\\desktop\\src\\pages\\assets\\AssetLibraryPage.vue", "source_location": "L507"}, {"caller_nid": "assetlibrarypage_formatshanghaidatetime", "callee": "part", "source_file": "C:\\Users\\wz\\Desktop\\py\\TK-OPS-ASSISTANT-v3\\apps\\desktop\\src\\pages\\assets\\AssetLibraryPage.vue", "source_location": "L507"}, {"caller_nid": "assetlibrarypage_formatshanghaidatetime", "callee": "part", "source_file": "C:\\Users\\wz\\Desktop\\py\\TK-OPS-ASSISTANT-v3\\apps\\desktop\\src\\pages\\assets\\AssetLibraryPage.vue", "source_location": "L507"}, {"caller_nid": "assetlibrarypage_formatshanghaidatetime", "callee": "part", "source_file": "C:\\Users\\wz\\Desktop\\py\\TK-OPS-ASSISTANT-v3\\apps\\desktop\\src\\pages\\assets\\AssetLibraryPage.vue", "source_location": "L507"}, {"caller_nid": "assetlibrarypage_totime", "callee": "getTime", "source_file": "C:\\Users\\wz\\Desktop\\py\\TK-OPS-ASSISTANT-v3\\apps\\desktop\\src\\pages\\assets\\AssetLibraryPage.vue", "source_location": "L511"}, {"caller_nid": "assetlibrarypage_totime", "callee": "isNaN", "source_file": "C:\\Users\\wz\\Desktop\\py\\TK-OPS-ASSISTANT-v3\\apps\\desktop\\src\\pages\\assets\\AssetLibraryPage.vue", "source_location": "L512"}]}